[
  {
    "name": "pages",

    "navItems": [
      {
        "name": "leads",
        "label": "Leads",
        "path": "/leads"
      },

      {
        "name": "customers",
        "label": "Customers",
        "path": "/customers"
      }
    ]
  },

  {
    "name": "my-account",
    "header": "My Account",

    "navItems": [
      {
        "name": "help",
        "label": "Help",
        "path": "/help"
      },
      {
        "name": "sign-out",
        "label": "Sign Out",
        "path": "/sign-out"
      }
    ]
  }
]
